santex/__init__.py
santex/anisotropy/__init__.py
santex/anisotropy/anisotropy.py
santex/anisotropy/map.py
santex/anisotropy/melt.py
santex/anisotropy/modalAnisotropy.py
santex/anisotropy/plot_seismic_velocity.py
santex/anisotropy/plot_vel_grid.py
santex/anisotropy/utils.py
santex/anisotropy/vtkplotter.py
santex/ebsd/__init__.py
santex/ebsd/_ctf_parser.py
santex/ebsd/calcGrainBoundary.py
santex/ebsd/crystal.py
santex/ebsd/ebsd.py
santex/ebsd/melt_tensor.py
santex/ebsd/rotateEBSD.py
santex/ebsd/saveEBSD.py
santex/isotropy/__init__.py
santex/isotropy/isotropy.py
santex/isotropy/data/materials.json
santex/material/__init__.py
santex/material/material.py
santex/material/data/derivatives_P.json
santex/material/data/derivatives_T.json
santex/material/data/materials_database.json
santex/tensor/__init__.py
santex/tensor/tensor.py
santex-1.2.3.dist-info/licenses/LICENSE
santex-1.2.3.dist-info/METADATA
santex-1.2.3.dist-info/WHEEL
santex-1.2.3.dist-info/top_level.txt
santex-1.2.3.dist-info/RECORD
