Metadata-Version: 2.4
Name: santex
Version: 1.2.3
Summary: SAnTeX is a Python library which calculates seismic anisotropy from full elastic tensor of rocks from modal mineral composition, crystallographic orientation, and a crystal stiffness tensor catalogue that accounts for the dependency of elasticity with pressure and temperature. SAnTex facilitates the processing and cleaning of EBSD data and calculation of Orientation Distribution Function (ODF) and Inverse pole figure (IPF)
Home-page: https://github.com/utpal-singh/SAnTex
Author: Utpal Singh
Author-email: utpal_singh@yahoo.com
License: GNU Lesser General Public License v3 (LGPLv3)
Keywords: python,seismic,seismic anisotropy,EBSD,Texture,Crystallography
Classifier: License :: OSI Approved :: GNU Lesser General Public License v3 (LGPLv3)
Classifier: Programming Language :: Python :: 3.9
Classifier: Programming Language :: Python :: 3.10
Classifier: Operating System :: OS Independent
License-File: LICENSE
Requires-Dist: joblib
Requires-Dist: pandas
Requires-Dist: matplotlib
Requires-Dist: numpy
Requires-Dist: vtk
Requires-Dist: tqdm
Requires-Dist: tabulate
Requires-Dist: scikit-learn
Requires-Dist: plotly
Requires-Dist: sphinx_rtd_theme
Requires-Dist: orix
Dynamic: author
Dynamic: author-email
Dynamic: classifier
Dynamic: description
Dynamic: description-content-type
Dynamic: home-page
Dynamic: keywords
Dynamic: license
Dynamic: license-file
Dynamic: requires-dist
Dynamic: summary
